<?xml version="1.0" encoding="utf-8" ?>
<dwsync>
<file name="categories_description.php" server="ftp.definitivetickets.com" local="133880040930455427" remote="132406488000000000" Dst="2" />
<file name="categories_lookup.php" server="ftp.definitivetickets.com" local="133880040931050286" remote="133201332000000000" Dst="2" />
<file name="compatibility.php" server="ftp.definitivetickets.com" local="133880040932401369" remote="132428952000000000" Dst="2" />
<file name="database.php" server="ftp.definitivetickets.com" local="133880040933016841" remote="132428952000000000" Dst="2" />
<file name="date_formats.php" server="ftp.definitivetickets.com" local="133880040933497391" remote="133201332000000000" Dst="2" />
<file name="db_backup.php" server="ftp.definitivetickets.com" local="133880040935284148" remote="132975864000000000" Dst="2" />
<file name="downloads_controller.php" server="ftp.definitivetickets.com" local="133880040935497036" remote="132406488000000000" Dst="2" />
<file name="ga_tickets.php" server="ftp.definitivetickets.com" local="133880040936537714" remote="132406488000000000" Dst="2" />
<file name="html_output.php" server="ftp.definitivetickets.com" local="133880040938634292" remote="133205652000000000" Dst="2" />
<file name="general.php" server="ftp.definitivetickets.com" local="133880040939660548" remote="133571160000000000" Dst="2" />
<file name="languages.php" server="ftp.definitivetickets.com" local="133880040938614411" remote="132406488000000000" Dst="2" />
<file name="localization.php" server="ftp.definitivetickets.com" local="133880040940433217" remote="132406488000000000" Dst="2" />
<file name="password_funcs.php" server="ftp.definitivetickets.com" local="133880040940882506" remote="132406488000000000" Dst="2" />
<file name="products_ticket.php" server="ftp.definitivetickets.com" local="133880040942302554" remote="133526196000000000" Dst="2" />
<file name="sessions.php" server="ftp.definitivetickets.com" local="133880040942884817" remote="132406488000000000" Dst="2" />
<file name="sessions_no_globals.php" server="ftp.definitivetickets.com" local="133880040942894854" remote="132406488000000000" Dst="2" />
<file name="shop_admin_members_general.php" server="ftp.definitivetickets.com" local="133880040944691943" remote="133215156000000000" Dst="2" />
<file name="validations.php" server="ftp.definitivetickets.com" local="133880040944702271" remote="132976728000000000" Dst="2" />
<file name="voucher_ticket.php" server="ftp.definitivetickets.com" local="133880040945908855" remote="133526196000000000" Dst="2" />
<file name="wallet_general.php" server="ftp.definitivetickets.com" local="133880040946512062" remote="132406488000000000" Dst="2" />
</dwsync>