{
  "ftp://ftptixadmin@definitivetickets.com@ftp.definitivetickets.com:21": {
    ".a2-optimized.db": {
      "type": "-",
      "size": 16384,
      "lmtime": 0,
      "modified": false
    },
    ".a2opt": {},
    ".bash_history": {
      "type": "-",
      "size": 311,
      "lmtime": 0,
      "modified": false
    },
    ".bash_logout": {
      "type": "-",
      "size": 18,
      "lmtime": 0,
      "modified": false
    },
    ".bash_profile": {
      "type": "-",
      "size": 176,
      "lmtime": 0,
      "modified": false
    },
    ".bashrc": {
      "type": "-",
      "size": 124,
      "lmtime": 0,
      "modified": false
    },
    ".cagefs": {},
    ".caldav": {},
    ".cl.selector": {},
    ".clwpos": {},
    ".contactemail": {
      "type": "-",
      "size": 17,
      "lmtime": 0,
      "modified": false
    },
    ".cpanel": {},
    ".cphorde": {},
    ".dns": {
      "type": "-",
      "size": 21,
      "lmtime": 0,
      "modified": false
    },
    ".emacs": {
      "type": "-",
      "size": 500,
      "lmtime": 0,
      "modified": false
    },
    ".ftpquota": {
      "type": "-",
      "size": 18,
      "lmtime": 0,
      "modified": false
    },
    ".gemrc": {
      "type": "-",
      "size": 139,
      "lmtime": 0,
      "modified": false
    },
    ".htpasswds": {},
    ".imunify_patch_id": {
      "type": "-",
      "size": 106,
      "lmtime": 0,
      "modified": false
    },
    ".koality": {},
    ".lastlogin": {
      "type": "-",
      "size": 584,
      "lmtime": 0,
      "modified": false
    },
    ".memcached": {},
    ".myimunify_id": {
      "type": "-",
      "size": 102,
      "lmtime": 0,
      "modified": false
    },
    ".pearrc": {
      "type": "-",
      "size": 607,
      "lmtime": 0,
      "modified": false
    },
    ".razor": {},
    ".softaculous": {},
    ".spamassassin": {},
    ".spamassassinboxenable": {
      "type": "-",
      "size": 0,
      "lmtime": 0,
      "modified": false
    },
    ".spamassassinenable": {
      "type": "-",
      "size": 0,
      "lmtime": 0,
      "modified": false
    },
    ".subaccounts": {},
    ".trash": {},
    ".wp-toolkit-identifier": {
      "type": "-",
      "size": 684,
      "lmtime": 0,
      "modified": false
    },
    ".zshrc": {
      "type": "-",
      "size": 658,
      "lmtime": 0,
      "modified": false
    },
    "Manual Backups": {},
    "access-logs": {
      "type": "l",
      "size": 34,
      "lmtime": 0,
      "modified": false
    },
    "backup-11.28.2021_17-56-53_tixadmin.tar.gz": {
      "type": "-",
      "size": 251379069,
      "lmtime": 0,
      "modified": false
    },
    "backup-3.23.2022_07-15-43_tixadmin.tar.gz": {
      "type": "-",
      "size": 574673940,
      "lmtime": 0,
      "modified": false
    },
    "backup-3.23.2022_07-18-08_tixadmin.tar.gz": {
      "type": "-",
      "size": 574674409,
      "lmtime": 0,
      "modified": false
    },
    "backup-6.2.2022_10-00-13_tixadmin.tar.gz": {
      "type": "-",
      "size": 907866705,
      "lmtime": 0,
      "modified": false
    },
    "backup-6.2.2022_10-10-35_tixadmin.tar.gz": {
      "type": "-",
      "size": 907863139,
      "lmtime": 0,
      "modified": false
    },
    "backup-7.5.2021_02-33-27_tixadmin.tar.gz": {
      "type": "-",
      "size": 253667248,
      "lmtime": 0,
      "modified": false
    },
    "backup-7.5.2021_02-36-15_tixadmin.tar.gz": {
      "type": "-",
      "size": 253667488,
      "lmtime": 0,
      "modified": false
    },
    "bin": {},
    "cache": {},
    "definitivetickets.com": {},
    "etc": {},
    "ifyac.definitivetickets.org": {
      ".ftpquota": {
        "type": "-",
        "size": 17,
        "lmtime": 0,
        "modified": false
      },
      ".htaccess": {
        "type": "-",
        "size": 2565,
        "lmtime": 0,
        "modified": false
      },
      ".user.ini": {
        "type": "-",
        "size": 608,
        "lmtime": 0,
        "modified": false
      },
      ".well-known": {},
      "400.shtml": {
        "type": "-",
        "size": 229,
        "lmtime": 0,
        "modified": false
      },
      "401.shtml": {
        "type": "-",
        "size": 207,
        "lmtime": 0,
        "modified": false
      },
      "403.shtml": {
        "type": "-",
        "size": 203,
        "lmtime": 0,
        "modified": false
      },
      "404.shtml": {
        "type": "-",
        "size": 204,
        "lmtime": 0,
        "modified": false
      },
      "413.shtml": {
        "type": "-",
        "size": 216,
        "lmtime": 0,
        "modified": false
      },
      "500.shtml": {
        "type": "-",
        "size": 243,
        "lmtime": 0,
        "modified": false
      },
      "LICENSE": {
        "type": "-",
        "size": 14948,
        "lmtime": 0,
        "modified": false
      },
      "ML_Campaigns.php": {
        "type": "-",
        "size": 1071,
        "lmtime": 0,
        "modified": false
      },
      "ML_Lists.php": {
        "type": "-",
        "size": 701,
        "lmtime": 0,
        "modified": false
      },
      "ML_Subscribers.php": {
        "type": "-",
        "size": 1222,
        "lmtime": 0,
        "modified": false
      },
      "OLDaetrum,,mnybt": {},
      "account.php": {
        "type": "-",
        "size": 1067,
        "lmtime": 0,
        "modified": false
      },
      "account_close.php": {
        "type": "-",
        "size": 3042,
        "lmtime": 0,
        "modified": false
      },
      "account_data.php": {
        "type": "-",
        "size": 3020,
        "lmtime": 0,
        "modified": false
      },
      "account_edit.php": {
        "type": "-",
        "size": 6614,
        "lmtime": 0,
        "modified": false
      },
      "account_history.php": {
        "type": "-",
        "size": 991,
        "lmtime": 0,
        "modified": false
      },
      "account_history_info.php": {
        "type": "-",
        "size": 2152,
        "lmtime": 0,
        "modified": false
      },
      "account_newsletters.php": {
        "type": "-",
        "size": 2653,
        "lmtime": 0,
        "modified": false
      },
      "account_password.php": {
        "type": "-",
        "size": 4016,
        "lmtime": 0,
        "modified": false
      },
      "account_password_first.php": {
        "type": "-",
        "size": 2424,
        "lmtime": 0,
        "modified": false
      },
      "account_ticket.php": {
        "type": "-",
        "size": 35447,
        "lmtime": 0,
        "modified": false
      },
      "add_checkout_success.php": {
        "type": "-",
        "size": 901,
        "lmtime": 0,
        "modified": false
      },
      "address_book.php": {
        "type": "-",
        "size": 990,
        "lmtime": 0,
        "modified": false
      },
      "address_book_process.php": {
        "type": "-",
        "size": 10872,
        "lmtime": 0,
        "modified": false
      },
      "ajax_checkout_payment_address.php": {
        "type": "-",
        "size": 19017,
        "lmtime": 0,
        "modified": false
      },
      "android-icon-192x192.png": {
        "type": "-",
        "size": 33608,
        "lmtime": 0,
        "modified": false
      },
      "autologin.php": {
        "type": "-",
        "size": 2851,
        "lmtime": 0,
        "modified": false
      },
      "barcode.php": {
        "type": "-",
        "size": 723,
        "lmtime": 0,
        "modified": false
      },
      "bor_checkout_success.php": {
        "type": "-",
        "size": 2590,
        "lmtime": 0,
        "modified": false
      },
      "bor_listings.php": {
        "type": "-",
        "size": 1584,
        "lmtime": 0,
        "modified": false
      },
      "cache": {},
      "checkout_confirmation.php": {
        "type": "-",
        "size": 12262,
        "lmtime": 0,
        "modified": false
      },
      "checkout_payment.php": {
        "type": "-",
        "size": 10953,
        "lmtime": 0,
        "modified": false
      },
      "checkout_payment_address.php": {
        "type": "-",
        "size": 12540,
        "lmtime": 0,
        "modified": false
      },
      "checkout_payment_process.php": {
        "type": "-",
        "size": 530,
        "lmtime": 0,
        "modified": false
      },
      "checkout_process.php": {
        "type": "-",
        "size": 47273,
        "lmtime": 0,
        "modified": false
      },
      "checkout_process_free.php": {
        "type": "-",
        "size": 40510,
        "lmtime": 0,
        "modified": false
      },
      "checkout_process_refund.php": {
        "type": "-",
        "size": 37693,
        "lmtime": 0,
        "modified": false
      },
      "checkout_process_reservation.php": {
        "type": "-",
        "size": 12085,
        "lmtime": 0,
        "modified": false
      },
      "checkout_shipping.php": {
        "type": "-",
        "size": 9884,
        "lmtime": 0,
        "modified": false
      },
      "checkout_shipping_address.php": {
        "type": "-",
        "size": 10599,
        "lmtime": 0,
        "modified": false
      },
      "checkout_single.php": {
        "type": "-",
        "size": 24139,
        "lmtime": 0,
        "modified": false
      },
      "checkout_success.php": {
        "type": "-",
        "size": 5380,
        "lmtime": 0,
        "modified": false
      },
      "contact_us.php": {
        "type": "-",
        "size": 3278,
        "lmtime": 0,
        "modified": false
      },
      "cookie_usage.php": {
        "type": "-",
        "size": 750,
        "lmtime": 0,
        "modified": false
      },
      "coupon_code_ajax.php": {
        "type": "-",
        "size": 10813,
        "lmtime": 0,
        "modified": false
      },
      "create_account.php": {
        "type": "-",
        "size": 9275,
        "lmtime": 0,
        "modified": false
      },
      "create_account_success.php": {
        "type": "-",
        "size": 3205,
        "lmtime": 0,
        "modified": false
      },
      "custom.css": {
        "type": "-",
        "size": 208,
        "lmtime": 0,
        "modified": false
      },
      "debug_cart.php": {
        "type": "-",
        "size": 578,
        "lmtime": 0,
        "modified": false
      },
      "docs": {},
      "down_for_maintenance.php": {
        "type": "-",
        "size": 854,
        "lmtime": 0,
        "modified": false
      },
      "download": {},
      "download.php": {
        "type": "-",
        "size": 5549,
        "lmtime": 0,
        "modified": false
      },
      "draggable_ajax.php": {
        "type": "-",
        "size": 1105,
        "lmtime": 0,
        "modified": false
      },
      "error_log": {
        "type": "-",
        "size": 1100,
        "lmtime": 0,
        "modified": false
      },
      "ext": {},
      "facebook-share-code-after-body-tag.txt": {
        "type": "-",
        "size": 398,
        "lmtime": 0,
        "modified": false
      },
      "favicon-32x32.png": {
        "type": "-",
        "size": 2649,
        "lmtime": 0,
        "modified": false
      },
      "favicon.ico": {
        "type": "-",
        "size": 1150,
        "lmtime": 0,
        "modified": false
      },
      "featured_categories.php": {
        "type": "-",
        "size": 856,
        "lmtime": 0,
        "modified": false
      },
      "featured_categories_bydate.php": {
        "type": "-",
        "size": 860,
        "lmtime": 0,
        "modified": false
      },
      "featured_products.php": {
        "type": "-",
        "size": 852,
        "lmtime": 0,
        "modified": false
      },
      "getDetails.php": {
        "type": "-",
        "size": 789,
        "lmtime": 0,
        "modified": false
      },
      "gv_faq.php": {
        "type": "-",
        "size": 778,
        "lmtime": 0,
        "modified": false
      },
      "gzip_handler.php": {
        "type": "-",
        "size": 360,
        "lmtime": 0,
        "modified": false
      },
      "htaccess-sef.txt": {
        "type": "-",
        "size": 1270,
        "lmtime": 0,
        "modified": false
      },
      "ifyacadmin": {},
      "ifyacscan.php": {
        "type": "-",
        "size": 2029,
        "lmtime": 0,
        "modified": false
      },
      "images": {},
      "includes": {},
      "index.php": {
        "type": "-",
        "size": 14061,
        "lmtime": 0,
        "modified": false
      },
      "information.php": {
        "type": "-",
        "size": 1236,
        "lmtime": 0,
        "modified": false
      },
      "installation.pdf": {
        "type": "-",
        "size": 447052,
        "lmtime": 0,
        "modified": false
      },
      "login.php": {
        "type": "-",
        "size": 9382,
        "lmtime": 0,
        "modified": false
      },
      "logoff.php": {
        "type": "-",
        "size": 2426,
        "lmtime": 0,
        "modified": false
      },
      "multi_block.php": {
        "type": "-",
        "size": 3530,
        "lmtime": 0,
        "modified": false
      },
      "order_email_send.php": {
        "type": "-",
        "size": 17271,
        "lmtime": 0,
        "modified": false
      },
      "osconcert.jpg": {
        "type": "-",
        "size": 34792,
        "lmtime": 0,
        "modified": false
      },
      "osconcert.png": {
        "type": "-",
        "size": 5985,
        "lmtime": 0,
        "modified": false
      },
      "password_forgotten.php": {
        "type": "-",
        "size": 3691,
        "lmtime": 0,
        "modified": false
      },
      "password_reset.php": {
        "type": "-",
        "size": 5075,
        "lmtime": 0,
        "modified": false
      },
      "password_send.php": {
        "type": "-",
        "size": 3207,
        "lmtime": 0,
        "modified": false
      },
      "paypal_api_cancel.php": {
        "type": "-",
        "size": 6736,
        "lmtime": 0,
        "modified": false
      },
      "paypal_api_return.php": {
        "type": "-",
        "size": 10855,
        "lmtime": 0,
        "modified": false
      },
      "paypal_api_webhook.php": {
        "type": "-",
        "size": 13821,
        "lmtime": 0,
        "modified": false
      },
      "pdfinvoice.php": {
        "type": "-",
        "size": 34649,
        "lmtime": 0,
        "modified": false
      },
      "php.ini.bak": {
        "type": "-",
        "size": 578,
        "lmtime": 0,
        "modified": false
      },
      "phpinfo.php": {
        "type": "-",
        "size": 26,
        "lmtime": 0,
        "modified": false
      },
      "popup_conditions.php": {
        "type": "-",
        "size": 948,
        "lmtime": 0,
        "modified": false
      },
      "popup_image.php": {
        "type": "-",
        "size": 977,
        "lmtime": 0,
        "modified": false
      },
      "product_email_template.html": {
        "type": "-",
        "size": 5189,
        "lmtime": 0,
        "modified": false
      },
      "product_info.php": {
        "type": "-",
        "size": 35029,
        "lmtime": 0,
        "modified": false
      },
      "products_ticket.php": {
        "type": "-",
        "size": 35443,
        "lmtime": 0,
        "modified": false
      },
      "robots.txt": {
        "type": "-",
        "size": 222,
        "lmtime": 0,
        "modified": false
      },
      "scanner.php": {
        "type": "-",
        "size": 15715,
        "lmtime": 0,
        "modified": false
      },
      "scanner2.php": {
        "type": "-",
        "size": 11783,
        "lmtime": 0,
        "modified": false
      },
      "search_events.php": {
        "type": "-",
        "size": 1105,
        "lmtime": 0,
        "modified": false
      },
      "seatplan_ajax.php": {
        "type": "-",
        "size": 7715,
        "lmtime": 0,
        "modified": false
      },
      "services_print.php": {
        "type": "-",
        "size": 1743,
        "lmtime": 0,
        "modified": false
      },
      "shopping_cart.php": {
        "type": "-",
        "size": 1522,
        "lmtime": 0,
        "modified": false
      },
      "specials.php": {
        "type": "-",
        "size": 861,
        "lmtime": 0,
        "modified": false
      },
      "static_page.php": {
        "type": "-",
        "size": 4224,
        "lmtime": 0,
        "modified": false
      },
      "stripesca_failure.php": {
        "type": "-",
        "size": 5395,
        "lmtime": 0,
        "modified": false
      },
      "stripesca_redirect.php": {
        "type": "-",
        "size": 1854,
        "lmtime": 0,
        "modified": false
      },
      "stripesca_success.php": {
        "type": "-",
        "size": 7173,
        "lmtime": 0,
        "modified": false
      },
      "stripesca_webhook.php": {
        "type": "-",
        "size": 8968,
        "lmtime": 0,
        "modified": false
      },
      "templates": {},
      "tfpdf": {},
      "voucher_ticket.php": {
        "type": "-",
        "size": 36554,
        "lmtime": 0,
        "modified": false
      }
    },
    "ifyac.org": {},
    "logphperrors": {},
    "logs": {},
    "lscache": {},
    "mail": {},
    "old.ifyac.definitivetickets.org": {},
    "perl5": {},
    "php": {},
    "public_ftp": {},
    "public_html": {},
    "srbackups": {},
    "ssl": {},
    "staging.definitivetickets.com": {},
    "staging2.definitivetickets.com": {},
    "staging3.definitivetickets.com": {},
    "staging4.definitivetickets.com": {},
    "storage": {},
    "templates": {
      "content": {
        "checkout_payment.tpl.php": {
          "type": "-",
          "size": 23692,
          "lmtime": 1745153254799.4395,
          "modified": false
        }
      }
    },
    "tmp": {},
    "var": {},
    "www": {
      "type": "l",
      "size": 11,
      "lmtime": 0,
      "modified": false
    }
  },
  "$version": 1
}